pionex_python/__init__.py
pionex_python/__version__.py
pionex_python/internal/PionexExceptions.py
pionex_python/internal/RestClient.py
pionex_python/internal/WebsocketClient.py
pionex_python/internal/__init__.py
pionex_python/internal/generate_signature.py
pionex_python/restful/Account.py
pionex_python/restful/Common.py
pionex_python/restful/Markets.py
pionex_python/restful/Orders.py
pionex_python/restful/__init__.py
pionex_python/websocket/PrivateStream.py
pionex_python/websocket/PublicStream.py
pionex_python/websocket/__init__.py
pionex_python-1.0.6.dist-info/LICENSE
pionex_python-1.0.6.dist-info/METADATA
pionex_python-1.0.6.dist-info/WHEEL
pionex_python-1.0.6.dist-info/RECORD
