Metadata-Version: 2.1
Name: pionex_python
Version: 1.0.6
Summary: Connector library for Pionex REST and WS api.
License: MIT
Author: Leo Thern
Author-email: 47295238+LeoThern@users.noreply.github.com
Requires-Python: >=3.11,<4.0
Classifier: License :: OSI Approved :: MIT License
Classifier: Programming Language :: Python :: 3
Classifier: Programming Language :: Python :: 3.11
Classifier: Programming Language :: Python :: 3.12
Requires-Dist: requests (>=2.31.0,<3.0.0)
Requires-Dist: websocket-client (>=1.7.0,<2.0.0)
